enturclient/__init__.py
enturclient/api.py
enturclient/dto/__init__.py
enturclient/dto/estimated_call.py
enturclient/dto/place.py
enturclient/queries.py
enturclient-0.2.3.dist-info/LICENSE
enturclient-0.2.3.dist-info/WHEEL
enturclient-0.2.3.dist-info/METADATA
enturclient-0.2.3.dist-info/RECORD
