Metadata-Version: 2.1
Name: enturclient
Version: 0.2.3
Summary: An API client for public transport data from Entur.
Home-page: https://github.com/hfurubotten/enturclient
License: MIT
Author: Heine Furubotten
Author-email: hfurubotten@users.noreply.github.com
Requires-Python: >=3.8,<4.0
Classifier: Intended Audience :: Developers
Classifier: License :: OSI Approved :: MIT License
Classifier: Operating System :: OS Independent
Classifier: Programming Language :: Python :: 3
Classifier: Programming Language :: Python :: 3.10
Classifier: Programming Language :: Python :: 3.8
Classifier: Programming Language :: Python :: 3.9
Requires-Dist: aiohttp (>=3.7.4,<4.0.0)
Requires-Dist: async_timeout (>=3.0.1,<5.0)
Project-URL: Repository, https://github.com/hfurubotten/enturclient
